microsoft_agents_m365copilot_core/__init__.py
microsoft_agents_m365copilot_core/src/__init__.py
microsoft_agents_m365copilot_core/src/_constants.py
microsoft_agents_m365copilot_core/src/_enums.py
microsoft_agents_m365copilot_core/src/authentication/__init__.py
microsoft_agents_m365copilot_core/src/authentication/azure_identity_authentication_provider.py
microsoft_agents_m365copilot_core/src/base_request_adapter.py
microsoft_agents_m365copilot_core/src/client_factory.py
microsoft_agents_m365copilot_core/src/middleware/__init__.py
microsoft_agents_m365copilot_core/src/middleware/async_transport.py
microsoft_agents_m365copilot_core/src/middleware/options/__init__.py
microsoft_agents_m365copilot_core/src/middleware/options/agents_copilot_telemetry_handler_option.py
microsoft_agents_m365copilot_core/src/middleware/request_context.py
microsoft_agents_m365copilot_core/src/middleware/telemetry.py
microsoft_agents_m365copilot_core/src/py.typed.txt
microsoft_agents_m365copilot_core-1.0.0rc2.dist-info/LICENSE
microsoft_agents_m365copilot_core-1.0.0rc2.dist-info/METADATA
microsoft_agents_m365copilot_core-1.0.0rc2.dist-info/WHEEL
microsoft_agents_m365copilot_core-1.0.0rc2.dist-info/RECORD
