Metadata-Version: 2.3
Name: microsoft-agents-m365copilot-core
Version: 1.0.0rc2
Summary: Core component of the Microsoft Agents M365 Copilot Core Python SDK
License: MIT
Keywords: Copilot,Microsoft,OpenAPI,SDK,M365
Author: Microsoft
Author-email: graphtooling+ccspython@microsoft.com
Maintainer: Microsoft
Maintainer-email: graphtooling+ccspython@microsoft.com
Requires-Python: >=3.9,<4.0
Classifier: Development Status :: 5 - Production/Stable
Classifier: Intended Audience :: Developers
Classifier: License :: OSI Approved :: MIT License
Classifier: Operating System :: OS Independent
Classifier: Programming Language :: Python :: 3
Classifier: Programming Language :: Python :: 3.9
Classifier: Programming Language :: Python :: 3.10
Classifier: Programming Language :: Python :: 3.11
Classifier: Programming Language :: Python :: 3.12
Classifier: Programming Language :: Python :: 3.13
Classifier: Topic :: Software Development :: Libraries :: Python Modules
Requires-Dist: azure-identity (>=1.23.0,<2.0.0)
Requires-Dist: httpx[http2] (>=0.23.0)
Requires-Dist: microsoft-kiota-abstractions (>=1.8.0,<2.0.0)
Requires-Dist: microsoft-kiota-authentication-azure (>=1.8.0,<2.0.0)
Requires-Dist: microsoft-kiota-http (>=1.8.0,<2.0.0)
Project-URL: Documentation, https://github.com/microsoft/Agents-M365Copilot/tree/main/python/packages/microsoft_agents_m365copilot_core#readme
Project-URL: Homepage, https://github.com/microsoft/Agents-M365Copilot/tree/main/python
Project-URL: Repository, https://github.com/microsoft/Agents-M365Copilot
